{"GameId":"b121f620-f68a-5461-82ea-fa1231a0d797","TeamUnqiueId":"8f3c4fd2-e589-5b3f-b372-b820d1facdfd","TeamShortId":"st-kilda-b-grade-b820d1facdfd","TeamId":"62629441359b006e4e00016b","TeamName":"St Kilda B Grade","Grade":"UNKNOWN","HomeAway":"Away","OppositionName":"North Coburg B Grade","OppositionId":"62629441359b006e6d00016c","SeasonName":"Winter 2022","SeasonId":"6274bd981c83a091aa0a1119","Location":"UNKNOWN","Date":"2022-04-23","Result":"W","HomeRuns":1,"AwayRuns":17,"Players":[{"ShortId":"todd-clarkson-85a82b92ebbf","UniqueId":"311bb492-868f-55a3-bb65-85a82b92ebbf","Name":"Todd Clarkson","FirstName":"Todd","LastName":"Clarkson","GameChangerIds":["62629441359b00701200017f"],"Hitting":{"PA":4,"AB":3,"H":0,"TB":0,"Singles":0,"Doubles":0,"Triples":0,"HR":0,"RBI":0,"R":1,"BB":1,"SO":2,"SOL":1,"SF":0,"HBP":0,"AVG":".000","SLG":".000","OPS":".250","OBP":".250"}},{"ShortId":"mariano-favia-787d7a8c6059","UniqueId":"1ec25aae-143b-5021-82d1-787d7a8c6059","Name":"Mariano Favia","FirstName":"Mariano","LastName":"Favia","GameChangerIds":["62629441359b007035000183"],"Hitting":{"PA":5,"AB":4,"H":2,"TB":2,"Singles":2,"Doubles":0,"Triples":0,"HR":0,"RBI":1,"R":2,"BB":1,"SO":0,"SOL":0,"SF":0,"HBP":0,"AVG":".500","SLG":".500","OPS":"1.100","OBP":".600"}},{"ShortId":"fernando-figueroa-f7b9189e9049","UniqueId":"da23ca88-93cb-52fe-b210-f7b9189e9049","Name":"Fernando Figueroa","FirstName":"Fernando","LastName":"Figueroa","GameChangerIds":["62629441359b00700b00017e"],"Hitting":{"PA":4,"AB":3,"H":1,"TB":2,"Singles":0,"Doubles":1,"Triples":0,"HR":0,"RBI":2,"R":1,"BB":1,"SO":1,"SOL":0,"SF":0,"HBP":0,"AVG":".333","SLG":".667","OPS":"1.167","OBP":".500"}},{"ShortId":"daniel-hogg-a04cb7a35a9d","UniqueId":"a538ed3b-d19a-5dc2-9516-a04cb7a35a9d","Name":"Daniel Hogg","FirstName":"Daniel","LastName":"Hogg","GameChangerIds":["62629441359b00700000017d"],"Hitting":{"PA":2,"AB":1,"H":1,"TB":2,"Singles":0,"Doubles":1,"Triples":0,"HR":0,"RBI":0,"R":2,"BB":0,"SO":0,"SOL":0,"SF":0,"HBP":0,"AVG":"1.000","SLG":"2.000","OPS":"3.000","OBP":"1.000"}},{"ShortId":"millar-kuhl-c1c9e5658c89","UniqueId":"44a45487-96a7-5ea1-84de-c1c9e5658c89","Name":"Millar Kuhl","FirstName":"Millar","LastName":"Kuhl","GameChangerIds":["62629441359b007019000180"],"Hitting":{"PA":5,"AB":4,"H":3,"TB":6,"Singles":1,"Doubles":1,"Triples":1,"HR":0,"RBI":3,"R":3,"BB":1,"SO":0,"SOL":0,"SF":0,"HBP":0,"AVG":".750","SLG":"1.500","OPS":"2.300","OBP":".800"}},{"ShortId":"alan-ortiz-dc8e4526b7c6","UniqueId":"15576835-dae3-58ba-a124-dc8e4526b7c6","Name":"Alan Ortiz","FirstName":"Alan","LastName":"Ortiz","GameChangerIds":["62629441359b007029000182"],"Hitting":{"PA":4,"AB":3,"H":2,"TB":4,"Singles":1,"Doubles":0,"Triples":1,"HR":0,"RBI":2,"R":1,"BB":1,"SO":0,"SOL":0,"SF":0,"HBP":0,"AVG":".667","SLG":"1.333","OPS":"2.083","OBP":".750"}},{"ShortId":"paul-puskar-a71d8173c018","UniqueId":"deb38eb1-6dbd-555a-a659-a71d8173c018","Name":"Paul Puskar","FirstName":"Paul","LastName":"Puskar","GameChangerIds":["62629441359b007021000181"],"Hitting":{"PA":4,"AB":3,"H":1,"TB":2,"Singles":0,"Doubles":1,"Triples":0,"HR":0,"RBI":1,"R":2,"BB":1,"SO":0,"SOL":0,"SF":0,"HBP":0,"AVG":".333","SLG":".667","OPS":"1.167","OBP":".500"}},{"ShortId":"chan-rohan-63177622035a","UniqueId":"7c0ebd36-b630-5b41-acb0-63177622035a","Name":"Chan Rohan","FirstName":"Chan","LastName":"Rohan","GameChangerIds":["6263944135fc0093fd000270"],"Hitting":{"PA":2,"AB":1,"H":0,"TB":0,"Singles":0,"Doubles":0,"Triples":0,"HR":0,"RBI":0,"R":1,"BB":1,"SO":0,"SOL":0,"SF":0,"HBP":0,"AVG":".000","SLG":".000","OPS":".500","OBP":".500"}},{"ShortId":"adam-schoppe-8c00b1ef474c","UniqueId":"48623f52-9674-55c8-acd7-8c00b1ef474c","Name":"Adam Schoppe","FirstName":"Adam","LastName":"Schoppe","GameChangerIds":["62629441359b006ffb00017c"],"Hitting":{"PA":4,"AB":1,"H":1,"TB":2,"Singles":0,"Doubles":1,"Triples":0,"HR":0,"RBI":1,"R":2,"BB":2,"SO":0,"SOL":0,"SF":0,"HBP":1,"AVG":"1.000","SLG":"2.000","OPS":"3.000","OBP":"1.000"}},{"ShortId":"gabriel-valderrama-3164a7ea9a75","UniqueId":"8dbe857e-a278-53c2-a588-3164a7ea9a75","Name":"Gabriel Valderrama","FirstName":"Gabriel","LastName":"Valderrama","GameChangerIds":["62629441359b00703e000184"],"Hitting":{"PA":4,"AB":4,"H":1,"TB":1,"Singles":1,"Doubles":0,"Triples":0,"HR":0,"RBI":0,"R":2,"BB":0,"SO":1,"SOL":0,"SF":0,"HBP":0,"AVG":".250","SLG":".250","OPS":".500","OBP":".250"}}],"GameChangerGameId":"62629441359b006e7700016d","GameUrl":"https://gc.com/game-62629441359b006e7700016d","GameShortId":"st-kilda-b-grade-north-coburg-b-grade-2022-04-23-fa1231a0d797"}